piqtec/__init__.py
piqtec/api/__init__.py
piqtec/api/generic.py
piqtec/constants.py
piqtec/controller.py
piqtec/py.typed
piqtec/type_helpers.py
piqtec/unit/__init__.py
piqtec/unit/base.py
piqtec/unit/calendar.py
piqtec/unit/device.py
piqtec/unit/room.py
piqtec/unit/sunblind.py
piqtec/unit/system.py
piqtec/utils.py
piqtec-0.1.5.dist-info/licenses/LICENCE
piqtec-0.1.5.dist-info/WHEEL
piqtec-0.1.5.dist-info/METADATA
piqtec-0.1.5.dist-info/RECORD
