Metadata-Version: 2.4
Name: piqtec
Version: 0.1.5
Summary: A implementation of Python interface to the IQtec / Kobra smart home solutions.
Author: Štěpán Venclík
Author-email: Štěpán Venclík <stepan.venclik@gmail.com>
License-Expression: CC-BY-NC-SA-4.0
License-File: LICENCE
Requires-Dist: requests>=2.32.4
Requires-Python: >=3.13
